<?xml version="1.0" encoding="utf-8"?>
<baseline version="1.0">
    <file name="build/generated/compose/resourceGenerator/kotlin/commonResClass/writeopia/application/features/global_shell/generated/resources/Res.kt">
        <error line="2" column="1" source="standard:indent" />
        <error line="3" column="1" source="standard:indent" />
        <error line="6" column="9" source="standard:package-name" />
        <error line="8" column="1" source="standard:import-ordering" />
        <error line="16" column="1" source="standard:indent" />
        <error line="17" column="1" source="standard:indent" />
        <error line="18" column="1" source="standard:indent" />
        <error line="19" column="1" source="standard:indent" />
        <error line="20" column="1" source="standard:indent" />
        <error line="21" column="1" source="standard:indent" />
        <error line="22" column="1" source="standard:indent" />
        <error line="23" column="1" source="standard:indent" />
        <error line="24" column="1" source="standard:indent" />
        <error line="25" column="1" source="standard:indent" />
        <error line="26" column="1" source="standard:indent" />
        <error line="26" column="25" source="standard:wrapping" />
        <error line="26" column="25" source="standard:argument-list-wrapping" />
        <error line="27" column="1" source="standard:indent" />
        <error line="27" column="10" source="standard:wrapping" />
        <error line="27" column="11" source="standard:argument-list-wrapping" />
        <error line="29" column="1" source="standard:indent" />
        <error line="30" column="1" source="standard:indent" />
        <error line="31" column="1" source="standard:indent" />
        <error line="32" column="1" source="standard:indent" />
        <error line="33" column="1" source="standard:indent" />
        <error line="34" column="1" source="standard:indent" />
        <error line="35" column="1" source="standard:indent" />
        <error line="36" column="1" source="standard:indent" />
        <error line="37" column="1" source="standard:indent" />
        <error line="38" column="1" source="standard:indent" />
        <error line="39" column="1" source="standard:indent" />
        <error line="39" column="22" source="standard:wrapping" />
        <error line="39" column="22" source="standard:argument-list-wrapping" />
        <error line="40" column="1" source="standard:indent" />
        <error line="40" column="10" source="standard:wrapping" />
        <error line="40" column="11" source="standard:argument-list-wrapping" />
        <error line="42" column="1" source="standard:indent" />
        <error line="42" column="17" source="standard:class-naming" />
        <error line="44" column="1" source="standard:indent" />
        <error line="44" column="17" source="standard:class-naming" />
        <error line="46" column="1" source="standard:indent" />
        <error line="46" column="17" source="standard:class-naming" />
        <error line="48" column="1" source="standard:indent" />
        <error line="48" column="17" source="standard:class-naming" />
        <error line="50" column="1" source="standard:indent" />
        <error line="50" column="17" source="standard:class-naming" />
    </file>
    <file name="src/commonMain/kotlin/io/writeopia/global/shell/SideGlobalMenu.kt">
        <error line="58" column="19" source="standard:property-naming" />
        <error line="145" column="1" source="standard:no-consecutive-blank-lines" />
        <error line="303" column="34" source="standard:curly-spacing" />
        <error line="363" column="1" source="standard:indent" />
        <error line="364" column="1" source="standard:indent" />
        <error line="365" column="1" source="standard:indent" />
        <error line="366" column="1" source="standard:indent" />
        <error line="367" column="1" source="standard:indent" />
        <error line="368" column="1" source="standard:indent" />
    </file>
    <file name="src/commonMain/kotlin/io/writeopia/global/shell/viewmodel/GlobalShellKmpViewModel.kt">
        <error line="3" column="1" source="standard:import-ordering" />
        <error line="51" column="17" source="standard:property-naming" />
    </file>
    <file name="src/commonMain/kotlin/io/writeopia/global/shell/viewmodel/GlobalShellViewModel.kt">
        <error line="14" column="25" source="standard:colon-spacing" />
        <error line="19" column="5" source="standard:blank-line-before-declaration" />
        <error line="20" column="5" source="standard:blank-line-before-declaration" />
        <error line="21" column="5" source="standard:blank-line-before-declaration" />
    </file>
</baseline>
